pymoneroasync/__init__.py
pymoneroasync/_abc.py
pymoneroasync/_httpx.py
pymoneroasync/const.py
pymoneroasync/exceptions.py
pymoneroasync/models/__init__.py
pymoneroasync/models/daemon/__init__.py
pymoneroasync/models/daemon/inputs.py
pymoneroasync/models/daemon/outputs.py
pymoneroasync/rpc_error.py
pymoneroasync/sansio.py
pymoneroasync-0.1.0.dist-info/WHEEL
pymoneroasync-0.1.0.dist-info/METADATA
pymoneroasync-0.1.0.dist-info/RECORD
